{
  "posts": [
    {
      "id": "1",
      "title": "json-server",
      "author": "typicode"
    }
  ],
  "comments": [
    {
      "id": "1",
      "body": "some comment",
      "postId": "1"
    }
  ],
  "users": [
    {
      "id": "1",
      "username": "admin",
      "password": "123"
    }
  ],
  "profile": {
    "firstname": "Dito",
    "lastname": "Kurkchievi",
    "age": 22,
    "currency": "GEL",
    "country": "Georgia",
    "city": "Tbilisi",
    "username": "admin",
    "avatar": "https://upload.wikimedia.org/wikipedia/commons/thumb/4/42/Shaqi_jrvej.jpg/1200px-Shaqi_jrvej.jpg"
  }
}